tests/test_feedback.py
tests/test_wordle.py
wordle/__init__.py
wordle/__main__.py
wordle/cli.py
wordle/feedback.py
wordle/heuristics.py
wordle/lib.py
wordle/solutiontree.py
wordle/solver.py
wordle/types.py
wordle/utils.py
wordle/data/allowed_except_relevant.txt
wordle/data/allowed_words.txt
wordle/data/cat_hidden_answers.txt
wordle/data/original_hidden_answers.txt
wordle/data/pillars_of_doom.txt
wordle/data/relevant_words.txt
wordle/data/updated_words.txt
wordle/data/word_freqs_2019_valid.txt
wordle/data/wordlist_nyt20230701_hidden
wordle_solver-0.3.dist-info/LICENSE
wordle_solver-0.3.dist-info/METADATA
wordle_solver-0.3.dist-info/WHEEL
wordle_solver-0.3.dist-info/entry_points.txt
wordle_solver-0.3.dist-info/top_level.txt
wordle_solver-0.3.dist-info/RECORD
