Metadata-Version: 2.1
Name: wordle-solver
Version: 0.3
Summary: Utility for solving and exploring wordle puzzles.
Author: Daniel Mar
License: Apache-2.0
Project-URL: Homepage, https://github.com/dkmar/wordle
Project-URL: Changelog, https://github.com/dkmar/wordle/releases
Project-URL: Issues, https://github.com/dkmar/wordle/issues
Project-URL: CI, https://github.com/dkmar/wordle/actions
Classifier: License :: OSI Approved :: Apache Software License
Requires-Python: >=3.8
License-File: LICENSE
Requires-Dist: click
Requires-Dist: numpy
Provides-Extra: test
Requires-Dist: pytest ; extra == 'test'
